<?xml version="1.0" encoding="UTF-8"?>
<Скрипт Версия="3.3" Наименование="ввести сумму" Автор="Администратор" АдресИнтернет="" ИдентификаторТеста="ввести_сумму" Severity="Значительная" DefaultAPI="1cClientApp" DefaultBrowser="Chrome" DefaultPort="1539">
	<Logic>
		<Action>ввести сумму</Action>
		<Description>ввести сумму</Description>
		<Cost>0</Cost>
		<Preconditions Count="1">
			<Item>
				<Variable>сумма</Variable>
				<Value type="Строка">*</Value>
			</Item>
		</Preconditions>
		<Effects Count="1">
			<Item>
				<Variable>ввести сумму</Variable>
				<Value type="Булево">true</Value>
			</Item>
		</Effects>
	</Logic>
	<ТаблицаШагов КоличествоШагов="6">
		<Шаг UID="58b95db6-df87-4c2a-88bb-71299d42c06f" FUID="58b95db6-df87-4c2a-88bb-71299d42c06f" BFUID="00000000-0000-0000-0000-000000000000" PUID="00000000-0000-0000-0000-000000000000">
			<Свойства>
				<Активность>true</Активность>
				<Наименование>Подключение к тестируемому приложению</Наименование>
				<Описание/>
				<ТипОбъекта/>
				<ЗаголовокОбъекта/>
				<ЭтоГлавноеОкно>false</ЭтоГлавноеОкно>
				<ИмяПеременной/>
				<Действие>ПодключитьТестируемоеПриложение</Действие>
				<ИмяОбъекта/>
				<ДанныеКартинки>9</ДанныеКартинки>
				<Команда/>
				<ПродолжитьПриОшибке>false</ПродолжитьПриОшибке>
				<OutputText/>
				<CommandRef/>
				<Presentation/>
				<Direction/>
				<RowDescription/>
				<SwitchSelection>false</SwitchSelection>
				<Cancel>false</Cancel>
				<Area/>
				<CustomCodeClient>
					<![CDATA[]]></CustomCodeClient>
				<CustomCodeServer>
					<![CDATA[]]></CustomCodeServer>
				<ПредставлениеДанных/>
				<СвойстваПодключенияКлиентаТестирования/>
				<API/>
				<ИмяКлассаОбъекта/>
				<ИдентификаторОбъекта/>
				<Attribute/>
				<ОдинУровеньВниз>false</ОдинУровеньВниз>
				<ClickX/>
				<ClickY/>
				<xPath/>
				<Интервал>0</Интервал>
				<ИспользоватьВариантыПоиска>false</ИспользоватьВариантыПоиска>
				<ЭтоБлок>false</ЭтоБлок>
				<Library/>
				<ПутьБлокШагов/>
				<Goal/>
				<ИмяПараметра/>
				<ИмяПараметра2/>
				<УсловиеСравнения/>
				<Severity/>
				<ЗначениеПараметра Тип="Строка"/>
			</Свойства>
		</Шаг>
		<Шаг UID="91d464f5-ae86-485e-b038-b197afb8c737" FUID="91d464f5-ae86-485e-b038-b197afb8c737" BFUID="00000000-0000-0000-0000-000000000000" PUID="00000000-0000-0000-0000-000000000000">
			<Свойства>
				<Активность>true</Активность>
				<Наименование>Получить активное окно</Наименование>
				<Описание/>
				<ТипОбъекта>ClientApplicationWindow</ТипОбъекта>
				<ЗаголовокОбъекта>Поступление безналичных денежных средств (создание) *</ЗаголовокОбъекта>
				<ЭтоГлавноеОкно>false</ЭтоГлавноеОкно>
				<ИмяПеременной>ОкноПриложенияПоступлениеБезналичныхДенежныхСредствСоздание</ИмяПеременной>
				<Действие>ПолучитьАктивноеОкно</Действие>
				<ИмяОбъекта/>
				<ДанныеКартинки>2</ДанныеКартинки>
				<Команда/>
				<ПродолжитьПриОшибке>false</ПродолжитьПриОшибке>
				<OutputText/>
				<CommandRef/>
				<Presentation/>
				<Direction/>
				<RowDescription/>
				<SwitchSelection>false</SwitchSelection>
				<Cancel>false</Cancel>
				<Area/>
				<CustomCodeClient>
					<![CDATA[]]></CustomCodeClient>
				<CustomCodeServer>
					<![CDATA[]]></CustomCodeServer>
				<ПредставлениеДанных/>
				<СвойстваПодключенияКлиентаТестирования/>
				<API/>
				<ИмяКлассаОбъекта/>
				<ИдентификаторОбъекта/>
				<Attribute/>
				<ОдинУровеньВниз>false</ОдинУровеньВниз>
				<ClickX/>
				<ClickY/>
				<xPath/>
				<Интервал>0</Интервал>
				<ИспользоватьВариантыПоиска>false</ИспользоватьВариантыПоиска>
				<ЭтоБлок>false</ЭтоБлок>
				<Library/>
				<ПутьБлокШагов/>
				<Goal/>
				<ИмяПараметра/>
				<ИмяПараметра2/>
				<УсловиеСравнения/>
				<Severity/>
				<ЗначениеПараметра Тип="Строка"/>
			</Свойства>
		</Шаг>
		<Шаг UID="93aeab86-fa3e-4499-8cd2-f747a88a2925" FUID="93aeab86-fa3e-4499-8cd2-f747a88a2925" BFUID="00000000-0000-0000-0000-000000000000" PUID="91d464f5-ae86-485e-b038-b197afb8c737">
			<Свойства>
				<Активность>true</Активность>
				<Наименование>Найти поле формы "Сумма"</Наименование>
				<Описание/>
				<ТипОбъекта>FormField</ТипОбъекта>
				<ЗаголовокОбъекта>Сумма</ЗаголовокОбъекта>
				<ЭтоГлавноеОкно>false</ЭтоГлавноеОкно>
				<ИмяПеременной>ОкноПриложенияПоступлениеБезналичныхДенежныхСредствСозданиеГруппаГруппаСуммаПолеСумма</ИмяПеременной>
				<Действие>НайтиОбъект</Действие>
				<ИмяОбъекта>СуммаДокумента</ИмяОбъекта>
				<ДанныеКартинки>5</ДанныеКартинки>
				<Команда/>
				<ПродолжитьПриОшибке>false</ПродолжитьПриОшибке>
				<OutputText/>
				<CommandRef/>
				<Presentation/>
				<Direction/>
				<RowDescription/>
				<SwitchSelection>false</SwitchSelection>
				<Cancel>false</Cancel>
				<Area/>
				<CustomCodeClient>
					<![CDATA[]]></CustomCodeClient>
				<CustomCodeServer>
					<![CDATA[]]></CustomCodeServer>
				<ПредставлениеДанных/>
				<СвойстваПодключенияКлиентаТестирования/>
				<API/>
				<ИмяКлассаОбъекта/>
				<ИдентификаторОбъекта/>
				<Attribute/>
				<ОдинУровеньВниз>false</ОдинУровеньВниз>
				<ClickX/>
				<ClickY/>
				<xPath/>
				<Интервал>0</Интервал>
				<ИспользоватьВариантыПоиска>false</ИспользоватьВариантыПоиска>
				<ЭтоБлок>false</ЭтоБлок>
				<Library/>
				<ПутьБлокШагов/>
				<Goal/>
				<ИмяПараметра/>
				<ИмяПараметра2/>
				<УсловиеСравнения/>
				<Severity/>
				<ЗначениеПараметра Тип="Строка"/>
			</Свойства>
		</Шаг>
		<Шаг UID="c10ff20b-d172-42a9-a7c3-e01ef7888e23" FUID="c10ff20b-d172-42a9-a7c3-e01ef7888e23" BFUID="00000000-0000-0000-0000-000000000000" PUID="93aeab86-fa3e-4499-8cd2-f747a88a2925">
			<Свойства>
				<Активность>true</Активность>
				<Наименование>Команда : Активизировать</Наименование>
				<Описание/>
				<ТипОбъекта>FormField</ТипОбъекта>
				<ЗаголовокОбъекта>Активизировать</ЗаголовокОбъекта>
				<ЭтоГлавноеОкно>false</ЭтоГлавноеОкно>
				<ИмяПеременной>ОкноПриложенияПоступлениеБезналичныхДенежныхСредствСозданиеГруппаГруппаСуммаПолеСумма</ИмяПеременной>
				<Действие>Команда</Действие>
				<ИмяОбъекта/>
				<ДанныеКартинки>7</ДанныеКартинки>
				<Команда>Активизировать</Команда>
				<ПродолжитьПриОшибке>false</ПродолжитьПриОшибке>
				<OutputText/>
				<CommandRef/>
				<Presentation/>
				<Direction/>
				<RowDescription/>
				<SwitchSelection>false</SwitchSelection>
				<Cancel>false</Cancel>
				<Area/>
				<CustomCodeClient>
					<![CDATA[]]></CustomCodeClient>
				<CustomCodeServer>
					<![CDATA[]]></CustomCodeServer>
				<ПредставлениеДанных/>
				<СвойстваПодключенияКлиентаТестирования/>
				<API/>
				<ИмяКлассаОбъекта/>
				<ИдентификаторОбъекта/>
				<Attribute/>
				<ОдинУровеньВниз>false</ОдинУровеньВниз>
				<ClickX/>
				<ClickY/>
				<xPath/>
				<Интервал>0</Интервал>
				<ИспользоватьВариантыПоиска>false</ИспользоватьВариантыПоиска>
				<ЭтоБлок>false</ЭтоБлок>
				<Library/>
				<ПутьБлокШагов/>
				<Goal/>
				<ИмяПараметра/>
				<ИмяПараметра2/>
				<УсловиеСравнения/>
				<Severity/>
				<ЗначениеПараметра Тип="Строка"/>
			</Свойства>
		</Шаг>
		<Шаг UID="5eb827fd-57c4-4046-95cf-58703392a63b" FUID="5eb827fd-57c4-4046-95cf-58703392a63b" BFUID="00000000-0000-0000-0000-000000000000" PUID="93aeab86-fa3e-4499-8cd2-f747a88a2925">
			<Свойства>
				<Активность>true</Активность>
				<Наименование>Команда : ВвестиТекст</Наименование>
				<Описание/>
				<ТипОбъекта>FormField</ТипОбъекта>
				<ЗаголовокОбъекта>ВвестиТекст</ЗаголовокОбъекта>
				<ЭтоГлавноеОкно>false</ЭтоГлавноеОкно>
				<ИмяПеременной>ОкноПриложенияПоступлениеБезналичныхДенежныхСредствСозданиеГруппаГруппаСуммаПолеСумма</ИмяПеременной>
				<Действие>Команда</Действие>
				<ИмяОбъекта/>
				<ДанныеКартинки>7</ДанныеКартинки>
				<Команда>ВвестиТекст</Команда>
				<ПродолжитьПриОшибке>false</ПродолжитьПриОшибке>
				<OutputText>&amp;Сумма</OutputText>
				<CommandRef/>
				<Presentation/>
				<Direction/>
				<RowDescription/>
				<SwitchSelection>false</SwitchSelection>
				<Cancel>false</Cancel>
				<Area/>
				<CustomCodeClient>
					<![CDATA[]]></CustomCodeClient>
				<CustomCodeServer>
					<![CDATA[]]></CustomCodeServer>
				<ПредставлениеДанных/>
				<СвойстваПодключенияКлиентаТестирования/>
				<API/>
				<ИмяКлассаОбъекта/>
				<ИдентификаторОбъекта/>
				<Attribute/>
				<ОдинУровеньВниз>false</ОдинУровеньВниз>
				<ClickX/>
				<ClickY/>
				<xPath/>
				<Интервал>0</Интервал>
				<ИспользоватьВариантыПоиска>false</ИспользоватьВариантыПоиска>
				<ЭтоБлок>false</ЭтоБлок>
				<Library/>
				<ПутьБлокШагов/>
				<Goal/>
				<ИмяПараметра/>
				<ИмяПараметра2/>
				<УсловиеСравнения/>
				<Severity/>
				<ЗначениеПараметра Тип="Строка"/>
			</Свойства>
		</Шаг>
		<Шаг UID="e7bbb61d-1d1b-47ff-af02-3e9375edcbd0" FUID="e7bbb61d-1d1b-47ff-af02-3e9375edcbd0" BFUID="00000000-0000-0000-0000-000000000000" PUID="00000000-0000-0000-0000-000000000000">
			<Свойства>
				<Активность>true</Активность>
				<Наименование>Отключиться от тестируемого приложения</Наименование>
				<Описание/>
				<ТипОбъекта/>
				<ЗаголовокОбъекта/>
				<ЭтоГлавноеОкно>false</ЭтоГлавноеОкно>
				<ИмяПеременной/>
				<Действие>ЗакрытьТестируемоеПриложение</Действие>
				<ИмяОбъекта/>
				<ДанныеКартинки>10</ДанныеКартинки>
				<Команда/>
				<ПродолжитьПриОшибке>false</ПродолжитьПриОшибке>
				<OutputText/>
				<CommandRef/>
				<Presentation/>
				<Direction/>
				<RowDescription/>
				<SwitchSelection>false</SwitchSelection>
				<Cancel>false</Cancel>
				<Area/>
				<CustomCodeClient>
					<![CDATA[]]></CustomCodeClient>
				<CustomCodeServer>
					<![CDATA[]]></CustomCodeServer>
				<ПредставлениеДанных/>
				<СвойстваПодключенияКлиентаТестирования/>
				<API/>
				<ИмяКлассаОбъекта/>
				<ИдентификаторОбъекта/>
				<Attribute/>
				<ОдинУровеньВниз>false</ОдинУровеньВниз>
				<ClickX/>
				<ClickY/>
				<xPath/>
				<Интервал>0</Интервал>
				<ИспользоватьВариантыПоиска>false</ИспользоватьВариантыПоиска>
				<ЭтоБлок>false</ЭтоБлок>
				<Library/>
				<ПутьБлокШагов/>
				<Goal/>
				<ИмяПараметра/>
				<ИмяПараметра2/>
				<УсловиеСравнения/>
				<Severity/>
				<ЗначениеПараметра Тип="Строка"/>
			</Свойства>
		</Шаг>
	</ТаблицаШагов>
	<ПараметрыСценария КоличествоПараметров="1">
		<Параметр>
			<Имя>Сумма</Имя>
			<ТипДанных>Строка</ТипДанных>
			<Значение>1000</Значение>
			<Функция/>
			<КлиентСервер>false</КлиентСервер>
			<ЗатиратьРодительскиеЗначения>false</ЗатиратьРодительскиеЗначения>
			<ИзПодчиненных>false</ИзПодчиненных>
			<СвязьЛогика>сумма</СвязьЛогика>
		</Параметр>
	</ПараметрыСценария>
</Скрипт>